<?xml version="1.0" encoding="UTF-8"?><record_update table="sys_atf_step">
    <sys_atf_step action="DELETE">
        <active>false</active>
        <copied_from/>
        <description>Assert a response payload element '/result' is not empty</description>
        <display_name>Assert JSON Response Payload Element</display_name>
        <inputs/>
        <mugshots_cache_json/>
        <notes/>
        <order>17</order>
        <step_config display_value="Assert JSON Response Payload Element">afc114199f132200ef4afa7dc67fcf64</step_config>
        <sys_class_name>sys_atf_step</sys_class_name>
        <sys_created_by>jabbar.nurbash</sys_created_by>
        <sys_created_on>2024-07-09 11:22:18</sys_created_on>
        <sys_id>d9c6102d47570a10e9ddbf66706d4327</sys_id>
        <sys_mod_count>29</sys_mod_count>
        <sys_name>Assert JSON Response Payload Element</sys_name>
        <sys_package display_value="SmartIntegration" source="x_rptp_smartinte_0">eeb170fcff218a1019a8ffda7c4fd91f</sys_package>
        <sys_policy/>
        <sys_scope display_value="SmartIntegration">eeb170fcff218a1019a8ffda7c4fd91f</sys_scope>
        <sys_update_name>sys_atf_step_d9c6102d47570a10e9ddbf66706d4327</sys_update_name>
        <sys_updated_by>jabbar.nurbash</sys_updated_by>
        <sys_updated_on>2024-07-10 12:12:28</sys_updated_on>
        <table/>
        <test display_value="Quote HDFC Insurer">1336d82947570a10e9ddbf66706d4387</test>
        <timeout/>
        <warning_message/>
    </sys_atf_step>
    <sys_variable_value action="DELETE" query="document_key=d9c6102d47570a10e9ddbf66706d4327"/>
    <sys_variable_value action="DELETE">
        <document>sys_atf_step</document>
        <document_key>d9c6102d47570a10e9ddbf66706d4327</document_key>
        <order>120</order>
        <sys_class_name>sys_variable_value</sys_class_name>
        <sys_created_by>jabbar.nurbash</sys_created_by>
        <sys_created_on>2024-07-09 11:22:18</sys_created_on>
        <sys_id>0cd69ce947570a10e9ddbf66706d4314</sys_id>
        <sys_mod_count>0</sys_mod_count>
        <sys_updated_by>jabbar.nurbash</sys_updated_by>
        <sys_updated_on>2024-07-09 11:22:18</sys_updated_on>
        <value/>
        <variable display_value="Value">7b139c199f132200ef4afa7dc67fcfb3</variable>
    </sys_variable_value>
    <sys_variable_value action="DELETE">
        <document>sys_atf_step</document>
        <document_key>d9c6102d47570a10e9ddbf66706d4327</document_key>
        <order>100</order>
        <sys_class_name>sys_variable_value</sys_class_name>
        <sys_created_by>jabbar.nurbash</sys_created_by>
        <sys_created_on>2024-07-09 11:22:18</sys_created_on>
        <sys_id>80d69ce947570a10e9ddbf66706d4315</sys_id>
        <sys_mod_count>0</sys_mod_count>
        <sys_updated_by>jabbar.nurbash</sys_updated_by>
        <sys_updated_on>2024-07-09 11:22:18</sys_updated_on>
        <value>/result</value>
        <variable display_value="Element path">5a9258199f132200ef4afa7dc67fcfb4</variable>
    </sys_variable_value>
    <sys_variable_value action="DELETE">
        <document>sys_atf_step</document>
        <document_key>d9c6102d47570a10e9ddbf66706d4327</document_key>
        <order>110</order>
        <sys_class_name>sys_variable_value</sys_class_name>
        <sys_created_by>jabbar.nurbash</sys_created_by>
        <sys_created_on>2024-07-09 11:22:18</sys_created_on>
        <sys_id>ccd69ce947570a10e9ddbf66706d4314</sys_id>
        <sys_mod_count>0</sys_mod_count>
        <sys_updated_by>jabbar.nurbash</sys_updated_by>
        <sys_updated_on>2024-07-09 11:22:18</sys_updated_on>
        <value>exists</value>
        <variable display_value="Operation">2db298199f132200ef4afa7dc67fcfbc</variable>
    </sys_variable_value>
    <sys_element_mapping action="DELETE" query="table=var__m_atf_input_variable_afc114199f132200ef4afa7dc67fcf64^id=d9c6102d47570a10e9ddbf66706d4327"/>
    <sys_update_version action="INSERT_OR_UPDATE">
        <action>DELETE</action>
        <application display_value="SmartIntegration">eeb170fcff218a1019a8ffda7c4fd91f</application>
        <file_path/>
        <instance_id>59343d0ddb6dbddccaf99027c5961980</instance_id>
        <instance_name>ven06798</instance_name>
        <name>sys_atf_step_d9c6102d47570a10e9ddbf66706d4327</name>
        <payload><![CDATA[<?xml version="1.0" encoding="UTF-8"?><record_update table="sys_atf_step"><sys_atf_step action="INSERT_OR_UPDATE"><active>false</active><copied_from/><description>Assert a response payload element '/result' is not empty</description><display_name>Assert JSON Response Payload Element</display_name><inputs/><mugshots_cache_json/><notes/><order>17</order><step_config display_value="Assert JSON Response Payload Element">afc114199f132200ef4afa7dc67fcf64</step_config><sys_class_name>sys_atf_step</sys_class_name><sys_created_by>jabbar.nurbash</sys_created_by><sys_created_on>2024-07-09 11:22:18</sys_created_on><sys_id>d9c6102d47570a10e9ddbf66706d4327</sys_id><sys_mod_count>29</sys_mod_count><sys_name>Assert JSON Response Payload Element</sys_name><sys_package display_value="SmartIntegration" source="x_rptp_smartinte_0">eeb170fcff218a1019a8ffda7c4fd91f</sys_package><sys_policy/><sys_scope display_value="SmartIntegration">eeb170fcff218a1019a8ffda7c4fd91f</sys_scope><sys_update_name>sys_atf_step_d9c6102d47570a10e9ddbf66706d4327</sys_update_name><sys_updated_by>jabbar.nurbash</sys_updated_by><sys_updated_on>2024-07-10 12:12:28</sys_updated_on><table/><test display_value="Quote HDFC Insurer">1336d82947570a10e9ddbf66706d4387</test><timeout/><warning_message/></sys_atf_step><sys_variable_value action="delete_multiple" query="document_key=d9c6102d47570a10e9ddbf66706d4327"/><sys_variable_value action="INSERT_OR_UPDATE"><document>sys_atf_step</document><document_key>d9c6102d47570a10e9ddbf66706d4327</document_key><order>120</order><sys_class_name>sys_variable_value</sys_class_name><sys_created_by>jabbar.nurbash</sys_created_by><sys_created_on>2024-07-09 11:22:18</sys_created_on><sys_id>0cd69ce947570a10e9ddbf66706d4314</sys_id><sys_mod_count>0</sys_mod_count><sys_updated_by>jabbar.nurbash</sys_updated_by><sys_updated_on>2024-07-09 11:22:18</sys_updated_on><value/><variable display_value="Value">7b139c199f132200ef4afa7dc67fcfb3</variable></sys_variable_value><sys_variable_value action="INSERT_OR_UPDATE"><document>sys_atf_step</document><document_key>d9c6102d47570a10e9ddbf66706d4327</document_key><order>100</order><sys_class_name>sys_variable_value</sys_class_name><sys_created_by>jabbar.nurbash</sys_created_by><sys_created_on>2024-07-09 11:22:18</sys_created_on><sys_id>80d69ce947570a10e9ddbf66706d4315</sys_id><sys_mod_count>0</sys_mod_count><sys_updated_by>jabbar.nurbash</sys_updated_by><sys_updated_on>2024-07-09 11:22:18</sys_updated_on><value>/result</value><variable display_value="Element path">5a9258199f132200ef4afa7dc67fcfb4</variable></sys_variable_value><sys_variable_value action="INSERT_OR_UPDATE"><document>sys_atf_step</document><document_key>d9c6102d47570a10e9ddbf66706d4327</document_key><order>110</order><sys_class_name>sys_variable_value</sys_class_name><sys_created_by>jabbar.nurbash</sys_created_by><sys_created_on>2024-07-09 11:22:18</sys_created_on><sys_id>ccd69ce947570a10e9ddbf66706d4314</sys_id><sys_mod_count>0</sys_mod_count><sys_updated_by>jabbar.nurbash</sys_updated_by><sys_updated_on>2024-07-09 11:22:18</sys_updated_on><value>exists</value><variable display_value="Operation">2db298199f132200ef4afa7dc67fcfbc</variable></sys_variable_value><sys_element_mapping action="delete_multiple" query="table=var__m_atf_input_variable_afc114199f132200ef4afa7dc67fcf64^id=d9c6102d47570a10e9ddbf66706d4327"/></record_update>]]></payload>
        <payload_hash>-2057195393</payload_hash>
        <record_name>Assert JSON Response Payload Element</record_name>
        <reverted_from/>
        <source>45769fde47ed8610e9ddbf66706d4387</source>
        <source_table>sys_update_set</source_table>
        <state>previous</state>
        <sys_created_by>jabbar.nurbash</sys_created_by>
        <sys_created_on>2024-07-10 12:12:28</sys_created_on>
        <sys_id>38ebe53547d3ca10e9ddbf66706d433e</sys_id>
        <sys_mod_count>0</sys_mod_count>
        <sys_recorded_at>1909c8f32620000001</sys_recorded_at>
        <sys_updated_by>jabbar.nurbash</sys_updated_by>
        <sys_updated_on>2024-07-10 12:12:28</sys_updated_on>
        <type>Test Step</type>
        <update_guid>bcebe53520d3ca10b12bdcd6c3a98d3d</update_guid>
        <update_guid_history>bcebe53520d3ca10b12bdcd6c3a98d3d:-2057195393,a0bb21350cd3ca1084f33aacaeb8449d:-978186336,3f8be9f130d3ca106782091e9a43feac:100822721,a27b69f1c6d3ca10254717d16a45f63a:1179831778,8ac568795e1b8a10c635e0095dd2ad84:-2036126461,37a56479541b8a1055facd71c526e2b2:-957117404,f0956079e41b8a103641752a8d56a946:121891653,c77164f9c0d78a10abb0c5756da63734:1200900710,ec61a0f9d3d78a10080dd55ec6e52cad:934239566,e231a8b92ed78a105acc1e5e5fb2f6d4:2013248623,b61164b9ebd78a10ce402ec8bfd9d256:-1202709616,769c5cf9dd978a10049987073709c8e3:-123700559,5a5a1035ae978a1078c424b2ca4ade2a:-1338647816,d44a1cf159978a10543526b8f1042c6a:-259638759,f41adcb19c978a10569d450c7e661cd1:819370298,ccd69ce929570a103d2dc582ee0aa716:1898379355</update_guid_history>
    </sys_update_version>
    <sys_metadata_delete action="INSERT_OR_UPDATE">
        <sys_audit_delete/>
        <sys_class_name>sys_metadata_delete</sys_class_name>
        <sys_created_by>jabbar.nurbash</sys_created_by>
        <sys_created_on>2024-11-15 09:04:59</sys_created_on>
        <sys_db_object display_value="" name="sys_atf_step">sys_atf_step</sys_db_object>
        <sys_id>00d057bdf15244eb804bb0c28c5f4651</sys_id>
        <sys_metadata>d9c6102d47570a10e9ddbf66706d4327</sys_metadata>
        <sys_mod_count>0</sys_mod_count>
        <sys_name>Assert JSON Response Payload Element</sys_name>
        <sys_package display_value="SmartIntegration" source="x_rptp_smartinte_0">eeb170fcff218a1019a8ffda7c4fd91f</sys_package>
        <sys_parent/>
        <sys_policy/>
        <sys_scope display_value="SmartIntegration">eeb170fcff218a1019a8ffda7c4fd91f</sys_scope>
        <sys_scope_delete display_value="">369325a421bf4d1f809d3b2ab5baaae1</sys_scope_delete>
        <sys_update_name>sys_atf_step_d9c6102d47570a10e9ddbf66706d4327</sys_update_name>
        <sys_update_version display_value="sys_atf_step_d9c6102d47570a10e9ddbf66706d4327">38ebe53547d3ca10e9ddbf66706d433e</sys_update_version>
        <sys_updated_by>jabbar.nurbash</sys_updated_by>
        <sys_updated_on>2024-11-15 09:04:59</sys_updated_on>
    </sys_metadata_delete>
</record_update>
