<?xml version="1.0" encoding="UTF-8"?><record_update table="sys_atf_parameter_set">
    <sys_atf_parameter_set action="DELETE">
        <active>true</active>
        <copied_from/>
        <description>Frequency = PF003
Actual payload = 
Premium = 10000
DOB = 18/07/1964
ResponseCode = 400
PPT = 15
PT = 30</description>
        <order>71</order>
        <parameters/>
        <sys_class_name>sys_atf_parameter_set</sys_class_name>
        <sys_created_by>jabbar.nurbash</sys_created_by>
        <sys_created_on>2024-08-30 10:14:29</sys_created_on>
        <sys_id>f5f9774a4714d290e9ddbf66706d4302</sys_id>
        <sys_mod_count>9</sys_mod_count>
        <sys_name>71</sys_name>
        <sys_package display_value="SmartIntegration" source="x_rptp_smartinte_0">eeb170fcff218a1019a8ffda7c4fd91f</sys_package>
        <sys_policy/>
        <sys_scope display_value="SmartIntegration">eeb170fcff218a1019a8ffda7c4fd91f</sys_scope>
        <sys_update_name>sys_atf_parameter_set_f5f9774a4714d290e9ddbf66706d4302</sys_update_name>
        <sys_updated_by>jabbar.nurbash</sys_updated_by>
        <sys_updated_on>2024-09-08 06:57:14</sys_updated_on>
        <test display_value=" BALIC SWG - CW( IP == PH)">5217b30e47d0d290e9ddbf66706d431b</test>
        <u_actual_payload/>
        <u_dob>18/07/1964</u_dob>
        <u_frequency>PF003</u_frequency>
        <u_ppt>15</u_ppt>
        <u_premium>10000</u_premium>
        <u_pt>30</u_pt>
        <u_responsecode>400</u_responsecode>
    </sys_atf_parameter_set>
    <sys_variable_value action="DELETE" query="document_key=f5f9774a4714d290e9ddbf66706d4302"/>
    <sys_update_version action="INSERT_OR_UPDATE">
        <action>DELETE</action>
        <application display_value="SmartIntegration">eeb170fcff218a1019a8ffda7c4fd91f</application>
        <file_path/>
        <instance_id>59343d0ddb6dbddccaf99027c5961980</instance_id>
        <instance_name>ven06798</instance_name>
        <name>sys_atf_parameter_set_f5f9774a4714d290e9ddbf66706d4302</name>
        <payload><![CDATA[<?xml version="1.0" encoding="UTF-8"?><record_update table="sys_atf_parameter_set"><sys_atf_parameter_set action="INSERT_OR_UPDATE"><active>true</active><copied_from/><description>Frequency = PF003
Actual payload = 
Premium = 10000
DOB = 18/07/1964
ResponseCode = 400
PPT = 15
PT = 30</description><order>71</order><parameters/><sys_class_name>sys_atf_parameter_set</sys_class_name><sys_created_by>jabbar.nurbash</sys_created_by><sys_created_on>2024-08-30 10:14:29</sys_created_on><sys_id>f5f9774a4714d290e9ddbf66706d4302</sys_id><sys_mod_count>9</sys_mod_count><sys_name>71</sys_name><sys_package display_value="SmartIntegration" source="x_rptp_smartinte_0">eeb170fcff218a1019a8ffda7c4fd91f</sys_package><sys_policy/><sys_scope display_value="SmartIntegration">eeb170fcff218a1019a8ffda7c4fd91f</sys_scope><sys_update_name>sys_atf_parameter_set_f5f9774a4714d290e9ddbf66706d4302</sys_update_name><sys_updated_by>jabbar.nurbash</sys_updated_by><sys_updated_on>2024-09-08 06:57:14</sys_updated_on><test display_value=" BALIC SWG - CW( IP == PH)">5217b30e47d0d290e9ddbf66706d431b</test><u_actual_payload/><u_dob>18/07/1964</u_dob><u_frequency>PF003</u_frequency><u_ppt>15</u_ppt><u_premium>10000</u_premium><u_pt>30</u_pt><u_responsecode>400</u_responsecode></sys_atf_parameter_set><sys_variable_value action="delete_multiple" query="document_key=f5f9774a4714d290e9ddbf66706d4302"/></record_update>]]></payload>
        <payload_hash>-773027576</payload_hash>
        <record_name>71</record_name>
        <reverted_from/>
        <source>efd887004728d2d0e9ddbf66706d4346</source>
        <source_table>sys_update_set</source_table>
        <state>previous</state>
        <sys_created_by>jabbar.nurbash</sys_created_by>
        <sys_created_on>2024-09-08 06:57:14</sys_created_on>
        <sys_id>b313a949ff28521019a8ffda7c4fd9c3</sys_id>
        <sys_mod_count>0</sys_mod_count>
        <sys_recorded_at>191d06c257c0000001</sys_recorded_at>
        <sys_updated_by>jabbar.nurbash</sys_updated_by>
        <sys_updated_on>2024-09-08 06:57:14</sys_updated_on>
        <type>Test Run Data Set</type>
        <update_guid>3b13a9491b285210966ce8d3fbb631c2</update_guid>
        <update_guid_history>3b13a9491b285210966ce8d3fbb631c2:-773027576,90e1a585f62852107202855400fc5696:-1806156633,2daa1fd04fa856d0c52b93ec433b397f:-773027576,95cfbcc893e092d0a5b8639c3a74504b:1886421544,02fd704802e092d00c7fd3893e40a1e5:-1951593944,839d549e9e98d290ac4572ad120063e0:-316075768,35f9774aba14d290d63e0b2c620ea725:1319442408</update_guid_history>
    </sys_update_version>
    <sys_metadata_delete action="INSERT_OR_UPDATE">
        <sys_audit_delete/>
        <sys_class_name>sys_metadata_delete</sys_class_name>
        <sys_created_by>jabbar.nurbash</sys_created_by>
        <sys_created_on>2024-11-15 09:06:25</sys_created_on>
        <sys_db_object display_value="" name="sys_atf_parameter_set">sys_atf_parameter_set</sys_db_object>
        <sys_id>348e8549d9514298adf32059cb739f04</sys_id>
        <sys_metadata>f5f9774a4714d290e9ddbf66706d4302</sys_metadata>
        <sys_mod_count>0</sys_mod_count>
        <sys_name>71</sys_name>
        <sys_package display_value="SmartIntegration" source="x_rptp_smartinte_0">eeb170fcff218a1019a8ffda7c4fd91f</sys_package>
        <sys_parent/>
        <sys_policy/>
        <sys_scope display_value="SmartIntegration">eeb170fcff218a1019a8ffda7c4fd91f</sys_scope>
        <sys_scope_delete display_value="">369325a421bf4d1f809d3b2ab5baaae1</sys_scope_delete>
        <sys_update_name>sys_atf_parameter_set_f5f9774a4714d290e9ddbf66706d4302</sys_update_name>
        <sys_update_version display_value="sys_atf_parameter_set_f5f9774a4714d290e9ddbf66706d4302">b313a949ff28521019a8ffda7c4fd9c3</sys_update_version>
        <sys_updated_by>jabbar.nurbash</sys_updated_by>
        <sys_updated_on>2024-11-15 09:06:25</sys_updated_on>
    </sys_metadata_delete>
</record_update>
