<?xml version="1.0" encoding="UTF-8"?><record_update table="sys_atf_parameter_set">
    <sys_atf_parameter_set action="DELETE">
        <active>true</active>
        <copied_from/>
        <description>Frequency = PF003
Actual payload = 
Premium = 100000
DOB = 01/01/2024
ResponseCode = 400
PPT = 5
PT = 20</description>
        <order>29</order>
        <parameters/>
        <sys_class_name>sys_atf_parameter_set</sys_class_name>
        <sys_created_by>jabbar.nurbash</sys_created_by>
        <sys_created_on>2024-08-30 07:21:31</sys_created_on>
        <sys_id>cc62db8e479c9290e9ddbf66706d43ad</sys_id>
        <sys_mod_count>6</sys_mod_count>
        <sys_name>29</sys_name>
        <sys_package display_value="SmartIntegration" source="x_rptp_smartinte_0">eeb170fcff218a1019a8ffda7c4fd91f</sys_package>
        <sys_policy/>
        <sys_scope display_value="SmartIntegration">eeb170fcff218a1019a8ffda7c4fd91f</sys_scope>
        <sys_update_name>sys_atf_parameter_set_cc62db8e479c9290e9ddbf66706d43ad</sys_update_name>
        <sys_updated_by>jabbar.nurbash</sys_updated_by>
        <sys_updated_on>2024-09-09 09:21:20</sys_updated_on>
        <test display_value=" BALIC SWG - W( IP == PH)">feac8b8e475c9290e9ddbf66706d43d8</test>
        <u_actual_payload/>
        <u_dob>01/01/2024</u_dob>
        <u_frequency>PF003</u_frequency>
        <u_ppt>5</u_ppt>
        <u_premium>100000</u_premium>
        <u_pt>20</u_pt>
        <u_responsecode>400</u_responsecode>
    </sys_atf_parameter_set>
    <sys_variable_value action="DELETE" query="document_key=cc62db8e479c9290e9ddbf66706d43ad"/>
    <sys_update_version action="INSERT_OR_UPDATE">
        <action>DELETE</action>
        <application display_value="SmartIntegration">eeb170fcff218a1019a8ffda7c4fd91f</application>
        <file_path/>
        <instance_id>59343d0ddb6dbddccaf99027c5961980</instance_id>
        <instance_name>ven06798</instance_name>
        <name>sys_atf_parameter_set_cc62db8e479c9290e9ddbf66706d43ad</name>
        <payload><![CDATA[<?xml version="1.0" encoding="UTF-8"?><record_update table="sys_atf_parameter_set"><sys_atf_parameter_set action="INSERT_OR_UPDATE"><active>true</active><copied_from/><description>Frequency = PF003
Actual payload = 
Premium = 100000
DOB = 01/01/2024
ResponseCode = 400
PPT = 5
PT = 20</description><order>29</order><parameters/><sys_class_name>sys_atf_parameter_set</sys_class_name><sys_created_by>jabbar.nurbash</sys_created_by><sys_created_on>2024-08-30 07:21:31</sys_created_on><sys_id>cc62db8e479c9290e9ddbf66706d43ad</sys_id><sys_mod_count>6</sys_mod_count><sys_name>29</sys_name><sys_package display_value="SmartIntegration" source="x_rptp_smartinte_0">eeb170fcff218a1019a8ffda7c4fd91f</sys_package><sys_policy/><sys_scope display_value="SmartIntegration">eeb170fcff218a1019a8ffda7c4fd91f</sys_scope><sys_update_name>sys_atf_parameter_set_cc62db8e479c9290e9ddbf66706d43ad</sys_update_name><sys_updated_by>jabbar.nurbash</sys_updated_by><sys_updated_on>2024-09-09 09:21:20</sys_updated_on><test display_value=" BALIC SWG - W( IP == PH)">feac8b8e475c9290e9ddbf66706d43d8</test><u_actual_payload/><u_dob>01/01/2024</u_dob><u_frequency>PF003</u_frequency><u_ppt>5</u_ppt><u_premium>100000</u_premium><u_pt>20</u_pt><u_responsecode>400</u_responsecode></sys_atf_parameter_set><sys_variable_value action="delete_multiple" query="document_key=cc62db8e479c9290e9ddbf66706d43ad"/></record_update>]]></payload>
        <payload_hash>-453468742</payload_hash>
        <record_name>29</record_name>
        <reverted_from/>
        <source>efd887004728d2d0e9ddbf66706d4346</source>
        <source_table>sys_update_set</source_table>
        <state>previous</state>
        <sys_created_by>jabbar.nurbash</sys_created_by>
        <sys_created_on>2024-09-09 09:21:20</sys_created_on>
        <sys_id>a8bd835947ac1610e9ddbf66706d4306</sys_id>
        <sys_mod_count>0</sys_mod_count>
        <sys_recorded_at>191d6166f090000001</sys_recorded_at>
        <sys_updated_by>jabbar.nurbash</sys_updated_by>
        <sys_updated_on>2024-09-09 09:21:20</sys_updated_on>
        <type>Test Run Data Set</type>
        <update_guid>6cbd835949ac16109ddb37ec443ce505</update_guid>
        <update_guid_history>6cbd835949ac16109ddb37ec443ce505:-453468742,a3952b0d8ee8921068db0689e4fe26a5:125415544,86f60f1498e456d0bd4101665520f3d7:923372793,1d4bad047a6892d093cee3900da5feb6:125415544,a62e1cdeb198d2904cb29439adf09c9b:1692526712,4862db8e0c9c9290047eecb1231afeb3:220817720</update_guid_history>
    </sys_update_version>
    <sys_metadata_delete action="INSERT_OR_UPDATE">
        <sys_audit_delete/>
        <sys_class_name>sys_metadata_delete</sys_class_name>
        <sys_created_by>jabbar.nurbash</sys_created_by>
        <sys_created_on>2024-11-15 09:09:27</sys_created_on>
        <sys_db_object display_value="" name="sys_atf_parameter_set">sys_atf_parameter_set</sys_db_object>
        <sys_id>2373a77c804f4c60a78eb5dd267a7e10</sys_id>
        <sys_metadata>cc62db8e479c9290e9ddbf66706d43ad</sys_metadata>
        <sys_mod_count>0</sys_mod_count>
        <sys_name>29</sys_name>
        <sys_package display_value="SmartIntegration" source="x_rptp_smartinte_0">eeb170fcff218a1019a8ffda7c4fd91f</sys_package>
        <sys_parent/>
        <sys_policy/>
        <sys_scope display_value="SmartIntegration">eeb170fcff218a1019a8ffda7c4fd91f</sys_scope>
        <sys_scope_delete display_value="">369325a421bf4d1f809d3b2ab5baaae1</sys_scope_delete>
        <sys_update_name>sys_atf_parameter_set_cc62db8e479c9290e9ddbf66706d43ad</sys_update_name>
        <sys_update_version display_value="sys_atf_parameter_set_cc62db8e479c9290e9ddbf66706d43ad">a8bd835947ac1610e9ddbf66706d4306</sys_update_version>
        <sys_updated_by>jabbar.nurbash</sys_updated_by>
        <sys_updated_on>2024-11-15 09:09:27</sys_updated_on>
    </sys_metadata_delete>
</record_update>
