<?xml version="1.0" encoding="UTF-8"?><record_update table="sys_record_transformer">
    <sys_record_transformer action="DELETE">
        <active>true</active>
        <base_path/>
        <batch_size/>
        <description/>
        <name>IDR:IDR_REPLICATION_ENTRY:292f5c9e4798d290e9ddbf66706d439c:x_rptp_smartinte_0_in</name>
        <namespace display_value="IDR">00cddbf077102300c37525e36810616d</namespace>
        <output_strategy_sys_id/>
        <output_strategy_type/>
        <output_type/>
        <path/>
        <print_format>compact</print_format>
        <rule_sequence/>
        <sys_class_name>sys_record_transformer</sys_class_name>
        <sys_created_by>prasad.n</sys_created_by>
        <sys_created_on>2024-08-30 12:57:23</sys_created_on>
        <sys_id>444fd49247d8d290e9ddbf66706d43d7</sys_id>
        <sys_mod_count>0</sys_mod_count>
        <sys_name>IDR:IDR_REPLICATION_ENTRY:292f5c9e4798d290e9ddbf66706d439c:x_rptp_smartinte_0_in</sys_name>
        <sys_package display_value="SmartIntegration" source="x_rptp_smartinte_0">eeb170fcff218a1019a8ffda7c4fd91f</sys_package>
        <sys_policy/>
        <sys_scope display_value="SmartIntegration">eeb170fcff218a1019a8ffda7c4fd91f</sys_scope>
        <sys_update_name>sys_record_transformer_444fd49247d8d290e9ddbf66706d43d7</sys_update_name>
        <sys_updated_by>prasad.n</sys_updated_by>
        <sys_updated_on>2024-08-30 12:57:23</sys_updated_on>
    </sys_record_transformer>
    <sys_update_version action="INSERT_OR_UPDATE">
        <action>DELETE</action>
        <application display_value="SmartIntegration">eeb170fcff218a1019a8ffda7c4fd91f</application>
        <file_path/>
        <instance_id>59343d0ddb6dbddccaf99027c5961980</instance_id>
        <instance_name>ven06798</instance_name>
        <name>sys_record_transformer_444fd49247d8d290e9ddbf66706d43d7</name>
        <payload><![CDATA[<?xml version="1.0" encoding="UTF-8"?><record_update table="sys_record_transformer"><sys_record_transformer action="INSERT_OR_UPDATE"><active>true</active><base_path/><batch_size/><description/><name>IDR:IDR_REPLICATION_ENTRY:292f5c9e4798d290e9ddbf66706d439c:x_rptp_smartinte_0_in</name><namespace display_value="IDR">00cddbf077102300c37525e36810616d</namespace><output_strategy_sys_id/><output_strategy_type/><output_type/><path/><print_format>compact</print_format><rule_sequence/><sys_class_name>sys_record_transformer</sys_class_name><sys_created_by>prasad.n</sys_created_by><sys_created_on>2024-08-30 12:57:23</sys_created_on><sys_id>444fd49247d8d290e9ddbf66706d43d7</sys_id><sys_mod_count>0</sys_mod_count><sys_name>IDR:IDR_REPLICATION_ENTRY:292f5c9e4798d290e9ddbf66706d439c:x_rptp_smartinte_0_in</sys_name><sys_package display_value="SmartIntegration" source="x_rptp_smartinte_0">eeb170fcff218a1019a8ffda7c4fd91f</sys_package><sys_policy/><sys_scope display_value="SmartIntegration">eeb170fcff218a1019a8ffda7c4fd91f</sys_scope><sys_update_name>sys_record_transformer_444fd49247d8d290e9ddbf66706d43d7</sys_update_name><sys_updated_by>prasad.n</sys_updated_by><sys_updated_on>2024-08-30 12:57:23</sys_updated_on></sys_record_transformer></record_update>]]></payload>
        <payload_hash>-2095866416</payload_hash>
        <record_name>IDR:IDR_REPLICATION_ENTRY:292f5c9e4798d290e9ddbf66706d439c:x_rptp_smartinte_0_in</record_name>
        <reverted_from/>
        <source>41d86fb4ff91921019a8ffda7c4fd9a5</source>
        <source_table>sys_update_set</source_table>
        <state>previous</state>
        <sys_created_by>david.pedroso@snc</sys_created_by>
        <sys_created_on>2024-10-18 15:06:59</sys_created_on>
        <sys_id>c4d211c2ff9d9a1019a8ffda7c4fd978</sys_id>
        <sys_mod_count>0</sys_mod_count>
        <sys_recorded_at>192a02ae9550000001</sys_recorded_at>
        <sys_updated_by>david.pedroso@snc</sys_updated_by>
        <sys_updated_on>2024-10-18 15:06:59</sys_updated_on>
        <type>Record Transformer</type>
        <update_guid>80d211c2379d9a10d0c48a8e421a8878</update_guid>
        <update_guid_history>80d211c2379d9a10d0c48a8e421a8878:0,044fd4924fd8d290781fed2027d545d8:1153321419</update_guid_history>
    </sys_update_version>
    <sys_metadata_delete action="INSERT_OR_UPDATE">
        <sys_audit_delete/>
        <sys_class_name>sys_metadata_delete</sys_class_name>
        <sys_created_by>prasad.n</sys_created_by>
        <sys_created_on>2024-10-18 15:07:00</sys_created_on>
        <sys_db_object display_value="" name="sys_record_transformer">sys_record_transformer</sys_db_object>
        <sys_id>1925ecd1574b4f7e886dc2aca6279ec1</sys_id>
        <sys_metadata>444fd49247d8d290e9ddbf66706d43d7</sys_metadata>
        <sys_mod_count>0</sys_mod_count>
        <sys_name>IDR:IDR_REPLICATION_ENTRY:292f5c9e4798d290e9ddbf66706d439c:x_rptp_smartinte_0_in</sys_name>
        <sys_package display_value="SmartIntegration" source="x_rptp_smartinte_0">eeb170fcff218a1019a8ffda7c4fd91f</sys_package>
        <sys_parent/>
        <sys_policy/>
        <sys_scope display_value="SmartIntegration">eeb170fcff218a1019a8ffda7c4fd91f</sys_scope>
        <sys_scope_delete display_value="">369325a421bf4d1f809d3b2ab5baaae1</sys_scope_delete>
        <sys_update_name>sys_record_transformer_444fd49247d8d290e9ddbf66706d43d7</sys_update_name>
        <sys_update_version display_value="sys_record_transformer_444fd49247d8d290e9ddbf66706d43d7">c4d211c2ff9d9a1019a8ffda7c4fd978</sys_update_version>
        <sys_updated_by>prasad.n</sys_updated_by>
        <sys_updated_on>2024-10-18 15:07:00</sys_updated_on>
    </sys_metadata_delete>
</record_update>
